http_text_cli/__init__.py
http_text_cli/http_interactions.py
http_text_cli/manage_processes.py
http_text_cli-1.0.0.dist-info/LICENSE
http_text_cli-1.0.0.dist-info/METADATA
http_text_cli-1.0.0.dist-info/WHEEL
http_text_cli-1.0.0.dist-info/top_level.txt
http_text_cli-1.0.0.dist-info/RECORD
