Metadata-Version: 2.1
Name: http-text-cli
Version: 1.0.0
Summary: Turns an HTTP (REST) api into a command line script you can test with TextTest
Author-email: Emily Bache <emily@bacheconsulting.com>
License: GNU LESSER GENERAL PUBLIC LICENSE
Project-URL: Homepage, https://github.com/texttest/http_text_cli
Project-URL: Bug Tracker, https://github.com/texttest/http_text_cli/issues
Classifier: Programming Language :: Python :: 3
Classifier: License :: OSI Approved :: GNU Lesser General Public License v3 or later (LGPLv3+)
Classifier: Operating System :: OS Independent
Requires-Python: >=3.7
License-File: LICENSE
